Workbook
Name Accounts_added_2026: 'Revenue Ramp'!$C$15
Name Accounts_added_2027: 'Revenue Ramp'!$D$15
Name Accounts_added_2028: 'Revenue Ramp'!$E$15
Name Accounts_added_2029: 'Revenue Ramp'!$F$15
Name Accounts_added_2030: 'Revenue Ramp'!$G$15
Name Annual_churn: 'Assumptions'!$C$21
Name Average_discount: 'Assumptions'!$C$13
Name Blended_seats_per_account: 'Assumptions'!$C$15
Name Gross_margin: 'Assumptions'!$C$20
Name International_scope: 'Sources & Appendix'!$C$16
Name List_price_per_seat: 'Assumptions'!$C$12
Name Micro_5_to_19_staff_Accounts_K: 'TAM Build'!$C$7
Name Micro_5_to_19_staff_Seats_per_account: 'TAM Build'!$D$7
Name Mid_100_to_200_staff_Accounts_K: 'TAM Build'!$C$9
Name Mid_100_to_200_staff_Seats_per_account: 'TAM Build'!$D$9
Name Net_new_logos_year_1: 'Assumptions'!$C$22
Name Penetration_growth: 'Assumptions'!$C$19
Name Price_per_seat_2026: 'Revenue Ramp'!$C$16
Name Price_per_seat_2027: 'Revenue Ramp'!$D$16
Name Price_per_seat_2028: 'Revenue Ramp'!$E$16
Name Price_per_seat_2029: 'Revenue Ramp'!$F$16
Name Price_per_seat_2030: 'Revenue Ramp'!$G$16
Name Public_sector_Accounts_K: 'TAM Build'!$C$10
Name Public_sector_Seats_per_account: 'TAM Build'!$D$10
Name Seat_expansion_rate: 'Sources & Appendix'!$C$15
Name Serviceable_share: 'Assumptions'!$C$8
Name Share_of_SAM_volume_2026: 'Revenue Ramp'!$C$14
Name Share_of_SAM_volume_2027: 'Revenue Ramp'!$D$14
Name Share_of_SAM_volume_2028: 'Revenue Ramp'!$E$14
Name Share_of_SAM_volume_2029: 'Revenue Ramp'!$F$14
Name Share_of_SAM_volume_2030: 'Revenue Ramp'!$G$14
Name Small_20_to_99_staff_Accounts_K: 'TAM Build'!$C$8
Name Small_20_to_99_staff_Seats_per_account: 'TAM Build'!$D$8
Name Sources_Appendix_Net_new_logos_year_1: 'Sources & Appendix'!$C$14
Name Target_segments: 'Assumptions'!$C$9
Name US_small_businesses_M: 'Assumptions'!$C$7
Name Year_1_penetration: 'Assumptions'!$C$18

Sheet Read Me
A1: Fieldnote: US SMB market sizing
A2: v1, built 2026-09-18
A5: Purpose
A6: This workbook sizes the US small and mid sized business market for Fieldnote seats and ramps revenue over five years. The TAM is built bottom up from account counts, seats per account and a discounted price per seat. The ramp takes one penetration assumption in year one and compounds it, so every output moves off a handful of blue cells on the Assumptions tab.
A8: Answer
A9: Fieldnote's serviceable seat market is about $1.9B, and the five year ramp reaches $124M of revenue at a 1.0% share of SAM in 2030.
A11: Contents
A12: Assumptions | B12: Every input the model reads: market frame, pricing, ramp and retention.
A13: TAM Build | B13: Bottom up TAM by segment, with the segment chart.
A14: Revenue Ramp | B14: Five year ramp, headline outputs and the revenue chart.
A15: Sources & Appendix | B15: Where each input came from, method notes and open items.
A17: Reading a Cell
A18: Blue | B18: an input, change it
A19: Black | B19: a formula, do not overwrite it
A20: Grey italic | B20: a note or a source, not a number the model uses
A22: Rules
A23: Blue cells are inputs. Change these and nothing else.
A24: Black cells are formulas. Do not type over them.
A25: Grey italic text is a note or a source, never a number the model reads.
A26: Every figure on Assumptions traces to a row on Sources & Appendix.
A27: Anything still reading TBD is unresolved and should not be quoted outside the team.

Sheet Assumptions
B2: Scope and approach
B3: The model covers US firms with 5 to 200 employees plus state and local public sector buyers. It prices on seats, not sites, and treats the discount as blended across segments rather than per deal. Everything downstream reads from the blue cells below.
B5: Market frame | D5: Refresh when the SBA profile updates
B6: Base year | C6: 2026 | D6: The model starts here
B7: US small businesses (M) | C7: 33.2 | D7: SBA 2024 small business profile
B8: Serviceable share | C8: 0.42 | D8: Firms with 5 to 200 employees
B9: Target segments | C9: 3
B11: Pricing
B12: List price per seat | C12: 480 | D12: Annual list, published rate card
B13: Average discount | C13: 0.15 | D13: Blended across the three segments
B14: Avg price | C14: =C12*(1-C13) | D14: Net price the ramp uses
B15: Blended seats per account | C15: 12 | D15: Weighted by the segment mix in TAM Build
B17: Ramp and retention
B18: Year 1 penetration | C18: 0.004 | D18: Share of total accounts won in year one
B19: Penetration growth | C19: 0.45 | D19: Applied to the prior year penetration
B20: Gross margin | C20: 0.78 | D20: Hosting and support only
B21: Annual churn | C21: 0.11 | D21: Logo churn, not seat churn
B22: Net new logos, year 1 | C22: TBD | D22: Sales has not signed off yet

Sheet TAM Build
B2: How the TAM is built
B3: Accounts by segment come from the licensed firmographic file, seats per account from the 2025 install base, and price per seat from Assumptions. TAM is accounts times seats times net price, so a change to the discount moves every row at once.
B5: Bottom up TAM by segment | G5: Accounts from the licensed firmographic file
B6: Segment | C6: Accounts (K) | D6: Seats per account | E6: Price per seat | F6: TAM ($M)
B7: Micro, 5 to 19 staff | C7: 4100 | D7: 6 | E7: ='Assumptions'!C14 | F7: =C7*1000*D7*E7/1000000
B8: Small, 20 to 99 staff | C8: 1450 | D8: 18 | E8: ='Assumptions'!C14 | F8: =C8*1000*D8*E8/1000000
B9: Mid, 100 to 200 staff | C9: 310 | D9: 65 | E9: ='Assumptions'!C14 | F9: =C9*1000*D9*E9/1000000
B10: Public sector | C10: 95 | D10: 40 | E10: ='Assumptions'!C14*0.85 | F10: =C10*1000*D10*E10/1000000
B11: Total | C11: =SUM(C7:C10) | F11: =SUM(F7:F10)

Sheet Revenue Ramp
B3: Five year revenue ramp | H3: Penetration compounds off year one
B4: Year | C4: Penetration | D4: Accounts | E4: Seats | F4: Revenue ($M) | G4: Gross profit ($M)
B5: 2026 | C5: ='Assumptions'!C18 | D5: ='TAM Build'!C11*1000*C5 | E5: =D5*'Assumptions'!C15 | F5: =E5*'Assumptions'!C14/1000000 | G5: =F5*'Assumptions'!C20
B6: 2027 | C6: =C5*(1+'Assumptions'!C19) | D6: ='TAM Build'!C11*1000*C6 | E6: =D6*'Assumptions'!C15 | F6: =E6*'Assumptions'!C14/1000000 | G6: =F6*'Assumptions'!C20
B7: 2028 | C7: =C6*(1+'Assumptions'!C19) | D7: ='TAM Build'!C11*1000*C7 | E7: =D7*'Assumptions'!C15 | F7: =E7*'Assumptions'!C14/1000000 | G7: =F7*'Assumptions'!C20
B8: 2029 | C8: =C7*(1+'Assumptions'!C19) | D8: ='TAM Build'!C11*1000*C8 | E8: =D8*'Assumptions'!C15 | F8: =E8*'Assumptions'!C14/1000000 | G8: =F8*'Assumptions'!C20
B9: 2030 | C9: =C8*(1+'Assumptions'!C19) | D9: ='TAM Build'!C11*1000*C9 | E9: =D9*'Assumptions'!C15 | F9: =E9*'Assumptions'!C14/1000000 | G9: =F9*'Assumptions'!C20
B10: Total | D10: =SUM(D5:D9) | E10: =SUM(E5:E9) | F10: =SUM(F5:F9) | G10: =SUM(G5:G9)
B12: Share of SAM by year | H12: Management assumption; the listed comparable is about 13% of 2026 SAM
B13: Line | C13: 2026 | D13: 2027 | E13: 2028 | F13: 2029 | G13: 2030
B14: Share of SAM volume | C14: 0.001 | D14: 0.003 | E14: 0.005 | F14: 0.008 | G14: 0.01
B15: Accounts added | C15: 40 | D15: 120 | E15: 200 | F15: 320 | G15: 400
B16: Price per seat | C16: 39 | D16: 40 | E16: 41 | F16: 42 | G16: 43
B18: Headline outputs
B19: Year 5 revenue ($M) | C19: =F9 | D19: Before any churn adjustment
B20: Year 5 gross profit ($M) | C20: =G9
B21: Share of TAM captured | C21: =F9/'TAM Build'!F11 | D21: Sanity check: under one percent is normal
B22: Revenue CAGR, year 1 to year 5 | C22: =(F9/F5)^(1/4)-1

Sheet Sources & Appendix
B3: Sources | G3: Every figure on Assumptions traces to a row here
B4: Input | C4: Source | D4: Published | E4: Detail | F4: Link
B5: US small businesses | C5: SBA Office of Advocacy | D5: 2024 | E5: Small business profile, firms with employees | F5: SBA profile
B6: Serviceable share | C6: Census County Business Patterns | D6: 2023 | E6: Employment size class 5 to 199 | F6: Census CBP
B7: Seats per account | C7: Fieldnote install base | D7: 2025 | E7: Median seats on paid plans | F7: Internal
B8: Average discount | C8: Fieldnote CRM | D8: 2025 | E8: Closed won deals, trailing four quarters | F8: Internal
B10: Method notes
B11: Accounts are counted at the firm level, not the establishment level, so multi site firms appear once. Public sector accounts sit outside the SBA universe and were added from the state and local procurement file. Nothing here is recalculated in Excel by the builder, so open the file once and let Excel compute.
B13: Open items
B14: Net new logos, year 1 | C14: TBD | D14: Sales to confirm the quota plan
B15: Seat expansion rate | C15: TBD | D15: Not yet modelled, would lift years 3 to 5
B16: International scope | C16: TBD | D16: Out of scope for this version
